[
  {
    "Id": "1254185",
    "ThreadId": "547960",
    "Html": "Will it be possible to for a Type Script code like this?<br />\n<pre><code>function firstToUpper(text) {\n// undefined on ES3, IE7 and below\n    var first = text[0]; // undefined\n    return first.toUpperCase() + text.substring(1).toLowerCase();\n}\nfirstToUpper(&quot;test&quot;);\n</code></pre>\n\nTo something like this for ES3?<br />\n<pre><code>function firstToUpper(text) {\n    var first = text.charAt(0);\n    return first.toUpperCase() + text.substring(1).toLowerCase();\n}\nfirstToUpper(&quot;test&quot;);\n</code></pre>\n\n",
    "PostedDate": "2014-06-08T12:07:07.423-07:00",
    "UserRole": null,
    "MarkedAsAnswerDate": null
  }
]