{
  "WorkItem": {
    "AffectedComponent": {
      "Name": "",
      "DisplayName": ""
    },
    "ClosedComment": "",
    "ClosedDate": null,
    "CommentCount": 1,
    "Custom": null,
    "Description": "I have recently begun getting the error 'The \"VsTsc\" task failed unexpectedly' whenever i try to build my web project. This is the build log:\r\n\r\nBuild FAILED.\r\n\r\n\"C:\\Users\\Morten\\Source\\Workspaces\\My Projects\\Projects\\Personal Book Reader\\PBR.Web\\PBR.Web.vbproj\" (default target) (1) ->\r\n(PreComputeCompileTypeScript target) -> \r\n  C:\\Program Files (x86)\\MSBuild\\Microsoft\\VisualStudio\\v12.0\\TypeScript\\Microsoft.TypeScript.targets(95,5): error MSB4018: The \"VsTsc\" task failed unexpectedly. [C:\\Users\\Morten\\Source\\Workspaces\\My Projects\\Projects\\Personal Book Reader\\PBR.Web\\PBR.Web.vbproj]\r\nC:\\Program Files (x86)\\MSBuild\\Microsoft\\VisualStudio\\v12.0\\TypeScript\\Microsoft.TypeScript.targets(95,5): error MSB4018: System.Resources.MissingManifestResourceException: Finner ikke noen ressurser som passer for den angitte kulturen eller den n›ytrale kulturen. Kontroller at TypeScript.Tasks.Strings.resources ble riktig innebygd eller koblet til samlingen TypeScript.Tasks under kompileringen, eller at alle de p†krevde satellittsamlingene kan lastes inn og er signert. [C:\\Users\\Morten\\Source\\Workspaces\\My Projects\\Projects\\Personal Book Reader\\PBR.Web\\PBR.Web.vbproj]\r\nC:\\Program Files (x86)\\MSBuild\\Microsoft\\VisualStudio\\v12.0\\TypeScript\\Microsoft.TypeScript.targets(95,5): error MSB4018:    ved System.Resources.ManifestBasedResourceGroveler.HandleResourceStreamMissing(String fileName) [C:\\Users\\Morten\\Source\\Workspaces\\My Projects\\Projects\\Personal Book Reader\\PBR.Web\\PBR.Web.vbproj]\r\nC:\\Program Files (x86)\\MSBuild\\Microsoft\\VisualStudio\\v12.0\\TypeScript\\Microsoft.TypeScript.targets(95,5): error MSB4018:    ved System.Resources.ManifestBasedResourceGroveler.GrovelForResourceSet(CultureInfo culture, Dictionary`2 localResourceSets, Boolean tryParents, Boolean createIfNotExists, StackCrawlMark& stackMark) [C:\\Users\\Morten\\Source\\Workspaces\\My Projects\\Projects\\Personal Book Reader\\PBR.Web\\PBR.Web.vbproj]\r\nC:\\Program Files (x86)\\MSBuild\\Microsoft\\VisualStudio\\v12.0\\TypeScript\\Microsoft.TypeScript.targets(95,5): error MSB4018:    ved System.Resources.ResourceManager.InternalGetResourceSet(CultureInfo requestedCulture, Boolean createIfNotExists, Boolean tryParents, StackCrawlMark& stackMark) [C:\\Users\\Morten\\Source\\Workspaces\\My Projects\\Projects\\Personal Book Reader\\PBR.Web\\PBR.Web.vbproj]\r\nC:\\Program Files (x86)\\MSBuild\\Microsoft\\VisualStudio\\v12.0\\TypeScript\\Microsoft.TypeScript.targets(95,5): error MSB4018:    ved System.Resources.ResourceManager.InternalGetResourceSet(CultureInfo culture, Boolean createIfNotExists, Boolean tryParents) [C:\\Users\\Morten\\Source\\Workspaces\\My Projects\\Projects\\Personal Book Reader\\PBR.Web\\PBR.Web.vbproj]\r\nC:\\Program Files (x86)\\MSBuild\\Microsoft\\VisualStudio\\v12.0\\TypeScript\\Microsoft.TypeScript.targets(95,5): error MSB4018:    ved System.Resources.ResourceManager.GetString(String name, CultureInfo culture) [C:\\Users\\Morten\\Source\\Workspaces\\My Projects\\Projects\\Personal Book Reader\\PBR.Web\\PBR.Web.vbproj]\r\nC:\\Program Files (x86)\\MSBuild\\Microsoft\\VisualStudio\\v12.0\\TypeScript\\Microsoft.TypeScript.targets(95,5): error MSB4018:    ved TypeScript.Tasks.Strings.get_NoFilesToCompile() [C:\\Users\\Morten\\Source\\Workspaces\\My Projects\\Projects\\Personal Book Reader\\PBR.Web\\PBR.Web.vbproj]\r\nC:\\Program Files (x86)\\MSBuild\\Microsoft\\VisualStudio\\v12.0\\TypeScript\\Microsoft.TypeScript.targets(95,5): error MSB4018:    ved TypeScript.Tasks.VsTsc.SkipTaskExecution() [C:\\Users\\Morten\\Source\\Workspaces\\My Projects\\Projects\\Personal Book Reader\\PBR.Web\\PBR.Web.vbproj]\r\nC:\\Program Files (x86)\\MSBuild\\Microsoft\\VisualStudio\\v12.0\\TypeScript\\Microsoft.TypeScript.targets(95,5): error MSB4018:    ved Microsoft.Build.Utilities.ToolTask.Execute() [C:\\Users\\Morten\\Source\\Workspaces\\My Projects\\Projects\\Personal Book Reader\\PBR.Web\\PBR.Web.vbproj]\r\nC:\\Program Files (x86)\\MSBuild\\Microsoft\\VisualStudio\\v12.0\\TypeScript\\Microsoft.TypeScript.targets(95,5): error MSB4018:    ved Microsoft.Build.BackEnd.TaskExecutionHost.Microsoft.Build.BackEnd.ITaskExecutionHost.Execute() [C:\\Users\\Morten\\Source\\Workspaces\\My Projects\\Projects\\Personal Book Reader\\PBR.Web\\PBR.Web.vbproj]\r\nC:\\Program Files (x86)\\MSBuild\\Microsoft\\VisualStudio\\v12.0\\TypeScript\\Microsoft.TypeScript.targets(95,5): error MSB4018:    ved Microsoft.Build.BackEnd.TaskBuilder.<ExecuteInstantiatedTask>d__20.MoveNext() [C:\\Users\\Morten\\Source\\Workspaces\\My Projects\\Projects\\Personal Book Reader\\PBR.Web\\PBR.Web.vbproj]\r\n\r\n    0 Warning(s)\r\n    1 Error(s)\r\n\r\nTime Elapsed 00:00:06.03",
    "LastUpdatedDate": "2014-10-28T10:57:04.583-07:00",
    "PlannedForRelease": "",
    "ReleaseVisibleToPublic": false,
    "Priority": {
      "Name": "Unassigned",
      "Severity": 0,
      "Id": 0
    },
    "ProjectName": "typescript",
    "ReportedDate": "2014-10-26T07:50:19.127-07:00",
    "Status": {
      "Name": "Proposed",
      "Id": 1
    },
    "ReasonClosed": {
      "Name": "Unassigned"
    },
    "Summary": "The \"VsTsc\" task failed unexpectedly. System.Resources.MissingManifestException",
    "Type": {
      "Name": "Unassigned",
      "Id": 5
    },
    "VoteCount": 1,
    "Id": 2647
  },
  "FileAttachments": [],
  "Comments": [
    {
      "Message": "This suddenly fixed itself today, so please disregard this error.",
      "PostedDate": "2014-10-28T10:57:04.583-07:00",
      "Id": 163441
    }
  ]
}