{
  "WorkItem": {
    "AffectedComponent": {
      "Name": "",
      "DisplayName": ""
    },
    "ClosedComment": "Thanks for logging this issue. We've moved to a new codebase on GitHub; please try your issue against the new compiler and log an issue on the GitHub site if it still reproduces.",
    "ClosedDate": "2014-07-21T17:29:54.25-07:00",
    "CommentCount": 3,
    "Custom": null,
    "Description": "I'm using TypeScript v1.0.1\r\n\r\nThe generated code puts the semicolon in its own line.\r\n```\r\n;((): void => {\r\n})();\r\n```\r\noutputs:\r\n```\r\n;\r\n(function () {\r\n})();\r\n```",
    "LastUpdatedDate": "2014-07-21T17:29:54.25-07:00",
    "PlannedForRelease": "",
    "ReleaseVisibleToPublic": false,
    "Priority": {
      "Name": "Unassigned",
      "Severity": 0,
      "Id": 0
    },
    "ProjectName": "typescript",
    "ReportedDate": "2014-06-19T05:07:00.16-07:00",
    "Status": {
      "Name": "Closed",
      "Id": 4
    },
    "ReasonClosed": {
      "Name": "External"
    },
    "Summary": "Tiny issue with defensive semicolon",
    "Type": {
      "Name": "Unassigned",
      "Id": 5
    },
    "VoteCount": 1,
    "Id": 2567
  },
  "FileAttachments": [],
  "Comments": [
    {
      "Message": "Does this not work the same?  I've seen examples of the latter as well. I think this comes down to cosmetic reasons.",
      "PostedDate": "2014-06-19T08:46:43.373-07:00",
      "Id": 150139
    },
    {
      "Message": "Nitpick:  I don't think the typescript compiler outputs ```... (): void =>```",
      "PostedDate": "2014-06-19T14:08:24.7-07:00",
      "Id": 150175
    },
    {
      "Message": "@AdamFreidin, obv... haha I fixed it.\n\nThat's what it really outputs though. :)",
      "PostedDate": "2014-06-20T03:00:48.72-07:00",
      "Id": 150321
    }
  ]
}