{
  "WorkItem": {
    "AffectedComponent": {
      "Name": "",
      "DisplayName": ""
    },
    "ClosedComment": "Thanks for reporting, this appears to be dead code. We're taking a look what we should do with this code.",
    "ClosedDate": "2013-04-10T16:48:32.947-07:00",
    "CommentCount": 0,
    "Custom": null,
    "Description": "TypeScript.ScriptEditRange is mentioned in diagnosticServices, but global search didn't find any other mention or indeed definition of that.",
    "LastUpdatedDate": "2013-04-10T16:48:32.947-07:00",
    "PlannedForRelease": "",
    "ReleaseVisibleToPublic": false,
    "Priority": {
      "Name": "Unassigned",
      "Severity": 0,
      "Id": 0
    },
    "ProjectName": "typescript",
    "ReportedDate": "2013-04-10T11:41:23.807-07:00",
    "Status": {
      "Name": "Closed",
      "Id": 4
    },
    "ReasonClosed": {
      "Name": "Postponed"
    },
    "Summary": "Unknown ScriptEditRange in diagnosticServices.ts",
    "Type": {
      "Name": "Unassigned",
      "Id": 5
    },
    "VoteCount": 1,
    "Id": 901
  },
  "FileAttachments": [],
  "Comments": []
}