{
  "WorkItem": {
    "AffectedComponent": {
      "Name": "",
      "DisplayName": ""
    },
    "ClosedComment": "Fixed in develop branch",
    "ClosedDate": "2013-06-13T11:22:40.287-07:00",
    "CommentCount": 1,
    "Custom": null,
    "Description": "The current implementation of static method will create a local closure with the same name of the method. While some keywords like \"try\" are valid method names but not valid variable names. This will create some difficulties when trying to use these keywords as static method names.\r\n\r\nNote that using a keyword as a non-static method name works fine now.\r\n\r\nPlease either allow it or give a compile error on it.",
    "LastUpdatedDate": "2014-01-10T10:34:33.287-08:00",
    "PlannedForRelease": "",
    "ReleaseVisibleToPublic": false,
    "Priority": {
      "Name": "Unassigned",
      "Severity": 0,
      "Id": 0
    },
    "ProjectName": "typescript",
    "ReportedDate": "2013-03-17T17:12:12.15-07:00",
    "Status": {
      "Name": "Closed",
      "Id": 4
    },
    "ReasonClosed": {
      "Name": "Fixed"
    },
    "Summary": "Allowing keywords as static method names.",
    "Type": {
      "Name": "Issue",
      "Id": 3
    },
    "VoteCount": 1,
    "Id": 824
  },
  "FileAttachments": [],
  "Comments": [
    {
      "Message": "Marking active",
      "PostedDate": "2013-03-18T09:40:04.603-07:00",
      "Id": 93551
    }
  ]
}