{
  "WorkItem": {
    "AffectedComponent": {
      "Name": "",
      "DisplayName": ""
    },
    "ClosedComment": "The fix should be visible in the upcoming release. Thanks!",
    "ClosedDate": "2014-03-31T17:33:04.447-07:00",
    "CommentCount": 1,
    "Custom": null,
    "Description": "If you create an interface which extends a generic Array:\r\n\r\n```\r\ninterface IThing extends Array<ISomething>{\r\n}\r\n```\r\n\r\nIt's fine. But if you compile and emit a .d.ts file, the output is:\r\n\r\n```\r\ninterface IThing extends ISomething[] {\r\n}\r\n```\r\n\r\nWhich is _not_ fine and does not compile.",
    "LastUpdatedDate": "2017-11-27T11:51:34.217-08:00",
    "PlannedForRelease": "",
    "ReleaseVisibleToPublic": false,
    "Priority": {
      "Name": "Unassigned",
      "Severity": 0,
      "Id": 0
    },
    "ProjectName": "typescript",
    "ReportedDate": "2013-11-28T18:34:02.667-08:00",
    "Status": {
      "Name": "Closed",
      "Id": 4
    },
    "ReasonClosed": {
      "Name": "Fixed"
    },
    "Summary": "Extending generic Array outputs incorrect .d.ts",
    "Type": {
      "Name": "Unassigned",
      "Id": 5
    },
    "VoteCount": 2,
    "Id": 1955
  },
  "FileAttachments": [],
  "Comments": [
    {
      "Message": "Just ran into this today. Needs to be fixed!",
      "PostedDate": "2014-02-17T16:22:52.85-08:00",
      "Id": 133891
    }
  ]
}