{
  "WorkItem": {
    "AffectedComponent": {
      "Name": "",
      "DisplayName": ""
    },
    "ClosedComment": "Believe this got addressed in the most recent spec update",
    "ClosedDate": "2014-07-21T13:17:16.12-07:00",
    "CommentCount": 1,
    "Custom": null,
    "Description": "In the grammar for ambient declarations, you have:\r\n\r\nAmbientDeclaration: \r\n     declare AmbientVariableDeclaration\r\n\r\nHowever, AmbientVariableDeclaration is equivalent to VariableDeclaration and only allows one variable declarator. It should really be AmbientVariableDeclarationList (and so on) since it should allow multiple declarators, and this is (in fact) what the compiler accepts.",
    "LastUpdatedDate": "2017-11-27T11:51:34.217-08:00",
    "PlannedForRelease": "",
    "ReleaseVisibleToPublic": false,
    "Priority": {
      "Name": "Unassigned",
      "Severity": 0,
      "Id": 0
    },
    "ProjectName": "typescript",
    "ReportedDate": "2014-04-01T13:10:56.007-07:00",
    "Status": {
      "Name": "Closed",
      "Id": 4
    },
    "ReasonClosed": {
      "Name": "Fixed"
    },
    "Summary": "AmbientDeclaration rule in spec grammar is incomplete",
    "Type": {
      "Name": "Unassigned",
      "Id": 5
    },
    "VoteCount": 1,
    "Id": 2370
  },
  "FileAttachments": [],
  "Comments": [
    {
      "Message": "Good catch. We'll update the spec.",
      "PostedDate": "2014-04-01T18:22:51.76-07:00",
      "Id": 140238
    }
  ]
}